{
  "generator-jhipster": {
    "jhipsterVersion": "4.0.8",
    "baseName": "moocyourlife",
    "packageName": "org.piotr.moocyourlife",
    "packageFolder": "org/piotr/moocyourlife",
    "serverPort": "8080",
    "authenticationType": "session",
    "hibernateCache": "ehcache",
    "clusteredHttpSession": false,
    "websocket": false,
    "databaseType": "sql",
    "devDatabaseType": "postgresql",
    "prodDatabaseType": "postgresql",
    "searchEngine": false,
    "messageBroker": false,
    "serviceDiscoveryType": false,
    "buildTool": "gradle",
    "enableSocialSignIn": true,
    "rememberMeKey": "45e58c36fc8fefdd3ac3dd6b26b6c321fe56d92f",
    "clientFramework": "angular2",
    "useSass": false,
    "clientPackageManager": "yarn",
    "applicationType": "monolith",
    "testFrameworks": [
      "gatling",
      "cucumber",
      "protractor"
    ],
    "jhiPrefix": "jhi",
    "enableTranslation": true,
    "nativeLanguage": "pl",
    "languages": [
      "pl",
      "en"
    ]
  }
}